Workbook

Sheet Precios y utilidad
A1: LISTA FINAL DE PRECIOS — COSTO, PRECIO DE VENTA Y UTILIDAD
A2: Costos verificados el 13-oct-2026. Precios con 40–50 % de utilidad sobre venta. Edita las celdas amarillas si cambia el precio en tienda.
A4: Producto | B4: Categoría | C4: Piezas por paquete | D4: Costo del paquete (MXN) | E4: Costo por pieza (MXN) | F4: Precio sugerido (MXN) | G4: Utilidad por pieza (MXN) | H4: Margen sobre venta (%) | I4: Utilidad por paquete (MXN) | J4: Estado del precio | K4: Conservación | L4: Notas | M4: Gasolina y luz por pieza (MXN) | N4: Desechables por pieza (MXN)
A5: Dumplings Bibigo (orden de 6) | B5: Comidas | C5: 6 | D5: 299 | E5: =IFERROR(D5/C5,0)+M5+N5 -> 56.535168 | F5: 100 | G5: =F5-E5 -> 43.464832 | H5: =IFERROR(G5/F5,0) -> 0.434648 | I5: =G5*C5 -> 260.78899 | J5: Referencia Costco 13-oct-2026 | K5: Congelado | L5: Costco: 36 piezas (6 charolas de 6) a ~$299; precio de nota de 2025, verificar en tienda. | M5: =Resumen!$B$11 -> 2.701835 | N5: 4
A6: Waffles Eggo (orden de 2) | B6: Comidas | C6: 36 | D6: 450.09 | E6: =IFERROR(D6/C6,0)+M6+N6 -> 18.204335 | F6: 40 | G6: =F6-E6 -> 21.795665 | H6: =IFERROR(G6/F6,0) -> 0.544892 | I6: =G6*C6 -> 784.64395 | J6: Verificado Costco 13-oct-2026 | K6: Congelado | L6: Costco 72 waffles ($360.09) = 36 órdenes + ~$90 de miel (estimado $2.50 por orden). Se sirve preparado. Cafeterías CDMX: $99–$174 por waffle. | M6: =Resumen!$B$11 -> 2.701835 | N6: 3
A7: Maruchan individual | B7: Comidas | C7: 12 | D7: 173.91 | E7: =IFERROR(D7/C7,0)+M7+N7 -> 18.694335 | F7: 35 | G7: =F7-E7 -> 16.305665 | H7: =IFERROR(G7/F7,0) -> 0.465876 | I7: =G7*C7 -> 195.66798 | J7: Verificado Sam's 13-oct-2026 | K7: Despensa | L7: Sam's caja 12. Walmart: $14 por pieza. Se sirve preparado con agua caliente. Súper: $14–$19 el vaso. | M7: =Resumen!$B$11 -> 2.701835 | N7: 1.5
A8: Starbucks Frappuccino 280 ml | B8: Café frío | C8: 12 | D8: 399 | E8: =IFERROR(D8/C8,0)+M8+N8 -> 35.951835 | F8: 70 | G8: =F8-E8 -> 34.048165 | H8: =IFERROR(G8/F8,0) -> 0.486402 | I8: =G8*C8 -> 408.57798 | J8: Verificado Costco 13-oct-2026 | K8: Despensa según etiqueta | L8: Costco 12×280 ml vidrio. Mantener frío al servir. Igual a OXXO ($47, Rappi). Margen bajo 40 %: caja de 12 cuesta $399. | M8: =Resumen!$B$11 -> 2.701835 | N8: 0
A9: Coca-Cola 355 ml PET | B9: Bebidas | C9: 24 | D9: 282.35 | E9: =IFERROR(D9/C9,0)+M9+N9 -> 14.466418 | F9: 25 | G9: =F9-E9 -> 10.533582 | H9: =IFERROR(G9/F9,0) -> 0.421343 | I9: =G9*C9 -> 252.80597 | J9: Verificado Sam's 13-oct-2026 | K9: Despensa | L9: Sam's 24×355 ml PET a $282.35 (antes $331.45). Reemplaza la de 600 ml. OXXO: $22.80 (Rappi). | M9: =Resumen!$B$11 -> 2.701835 | N9: 0
A10: Té Lipton 600 ml | B10: Bebidas | C10: 12 | D10: 152.41 | E10: =IFERROR(D10/C10,0)+M10+N10 -> 15.402668 | F10: 30 | G10: =F10-E10 -> 14.597332 | H10: =IFERROR(G10/F10,0) -> 0.486578 | I10: =G10*C10 -> 175.16798 | J10: Verificado Sam's 13-oct-2026 | K10: Despensa | L10: Sam's 12×600 ml surtido (verde, limón, durazno). Fuze Tea ($211.76) deja muy poco margen. Igual a OXXO ($24, Rappi). | M10: =Resumen!$B$11 -> 2.701835 | N10: 0
A11: Papas Sabritas surtidas | B11: Snacks | C11: 30 | D11: 369 | E11: =IFERROR(D11/C11,0)+M11+N11 -> 15.001835 | F11: 30 | G11: =F11-E11 -> 14.998165 | H11: =IFERROR(G11/F11,0) -> 0.499939 | I11: =G11*C11 -> 449.94495 | J11: Verificado Costco 13-oct-2026 | K11: Despensa | L11: Comprar en Costco ($351–$369). Sam's $475.69: deja muy poca ganancia. Igual a OXXO Sabritas 45 g ($22). | M11: =Resumen!$B$11 -> 2.701835 | N11: 0
A12: Galletas Emperador surtidas | B12: Galletas | C12: 12 | D12: 146.29 | E12: =IFERROR(D12/C12,0)+M12+N12 -> 14.892668 | F12: 30 | G12: =F12-E12 -> 15.107332 | H12: =IFERROR(G12/F12,0) -> 0.503578 | I12: =G12*C12 -> 181.28798 | J12: Verificado Sam's 13-oct-2026 | K12: Despensa | L12: Sam's 12 paquetes: $130.94–$146.29 (se usa el más alto). | M12: =Resumen!$B$11 -> 2.701835 | N12: 0
A13: Barras Nature Valley | B13: Snacks | C13: 24 | D13: 221.43 | E13: =IFERROR(D13/C13,0)+M13+N13 -> 11.928085 | F13: 25 | G13: =F13-E13 -> 13.071915 | H13: =IFERROR(G13/F13,0) -> 0.522877 | I13: =G13*C13 -> 313.72596 | J13: Verificado Amazon 13-oct-2026 | K13: Despensa | L13: Amazon 24 piezas: $213.80–$310. No comprar arriba de $260. | M13: =Resumen!$B$11 -> 2.701835 | N13: 0
A14: Cacahuates individuales | B14: Snacks | C14: 20 | D14: 180 | E14: =IFERROR(D14/C14,0)+M14+N14 -> 11.701835 | F14: 25 | G14: =F14-E14 -> 13.298165 | H14: =IFERROR(G14/F14,0) -> 0.531927 | I14: =G14*C14 -> 265.9633 | J14: SIN VERIFICAR — estimación | K14: Despensa | L14: No se encontró presentación de 20 piezas. Confirmar en tienda. | M14: =Resumen!$B$11 -> 2.701835 | N14: 0
A15: Galletas Oreo 42 g | B15: Galletas | C15: 30 | D15: 183.15 | E15: =IFERROR(D15/C15,0)+M15+N15 -> 8.806835 | F15: 20 | G15: =F15-E15 -> 11.193165 | H15: =IFERROR(G15/F15,0) -> 0.559658 | I15: =G15*C15 -> 335.79495 | J15: Verificado Sam's 13-oct-2026 | K15: Despensa | L15: Sam's 30×42 g. Ese precio era oferta de agosto; revisar en tienda. | M15: =Resumen!$B$11 -> 2.701835 | N15: 0

Sheet Resumen
A1: RESUMEN DE COMPRA Y UTILIDAD
A2: Costo total de compra | B2: =SUM('Precios y utilidad'!D5:D15) -> 2856.63
A3: Ingreso si se vende todo | B3: =SUMPRODUCT('Precios y utilidad'!C5:C15,'Precios y utilidad'!F5:F15) -> 7220
A4: Utilidad después de gastos | B4: =B3-B2-B8-B9-B12 -> 3624.37
A5: Margen sobre ventas | B5: =IFERROR(B4/B3,0) -> 0.50199
A6: Nota | B6: Utilidad después de gasolina, luz y desechables. No incluye mermas ni productos caducados.
A7: GASTOS DEL MES (EDITABLES)
A8: Gasolina al mes (2 viajes de 30 km a Costco/Sam’s) | B8: 144
A9: Luz comercial al mes (refrigerador + congelador) | B9: 445
A10: Piezas vendidas al mes | B10: 218
A11: Gasolina y luz por pieza | B11: =IFERROR((B8+B9)/B10,0) -> 2.701835
A12: Desechables del mes | B12: =SUMPRODUCT('Precios y utilidad'!C5:C15,'Precios y utilidad'!N5:N15) -> 150
A13: Supuestos | B13: Gasolina: 30 km ida y vuelta, 10 km/L, Magna ~$24/L, 2 viajes al mes. Luz: ~81 kWh/mes a ~$5.50/kWh (tarifa comercial). Si vendes más piezas al mes, baja el gasto por pieza.

Sheet Cómo usar
A1: CÓMO USAR EL ARCHIVO
A3: 1. Costos | B3: Costos verificados el 13-oct-2026 en Sam's, Costco y Amazon. Donde había rango se usó el precio más alto. Los cacahuates siguen sin verificar.
A4: 2. Celdas amarillas | B4: Edita piezas por paquete, costo del paquete y precio sugerido. Son datos de entrada.
A5: 3. Celdas verdes | B5: Costo por pieza, utilidad por pieza, margen y utilidad por paquete se calculan con fórmulas.
A6: 4. Precio justo | B6: Costo por pieza = costo de compra + gasolina y luz (hoja Resumen) + desechables. Precio ≈ 50 % de utilidad sobre ese costo total, redondeado a múltiplos de $5.
A7: 5. Utilidad | B7: La utilidad calculada es bruta. Resta transporte, energía, comisiones, mermas y productos caducados para estimar la ganancia neta.
A8: 6. Seguridad alimentaria | B8: Los productos congelados o refrigerados requieren mantener la cadena de frío. Respeta siempre la etiqueta y la fecha de caducidad.
A9: 7. Recomendación | B9: Antes de comprar en volumen, verifica que el precio y el número de piezas correspondan exactamente a la presentación local.
